ai_snow_trend/__init__.py
ai_snow_trend-1768557.14.476.dist-info/licenses/LICENSE
ai_snow_trend-1768557.14.476.dist-info/METADATA
ai_snow_trend-1768557.14.476.dist-info/WHEEL
ai_snow_trend-1768557.14.476.dist-info/top_level.txt
ai_snow_trend-1768557.14.476.dist-info/RECORD
