Metadata-Version: 2.4
Name: ai-snow-trend
Version: 1768557.14.476
Summary: High-quality integration for https://supermaker.ai/blog/how-to-make-ai-snow-trend-photos-for-tiktok-free-tutorial/
Home-page: https://supermaker.ai/blog/how-to-make-ai-snow-trend-photos-for-tiktok-free-tutorial/
Author: SuperMaker
Classifier: Programming Language :: Python :: 3
Classifier: License :: OSI Approved :: MIT License
Requires-Python: >=3.6
License-File: LICENSE
Dynamic: author
Dynamic: classifier
Dynamic: description
Dynamic: description-content-type
Dynamic: home-page
Dynamic: license-file
Dynamic: requires-python
Dynamic: summary
